<?xml version="1.0"?><!--mjs OpenSceneGraph Extensible Markup Language Process Description Script (OSG XML PDS)--><Environment>
	<FilePath>C:\mjs\OSG_DES_source\OSG_DES</FilePath>
	<FilePath>C:\mjs\OSG_DES_source\OSG_DES\Shaders</FilePath>
	<FilePath>C:\mjs\OSG_DES_source\OSG_DES\Media</FilePath>
	<FilePath>C:\mjs\OSG_DES_source\OSG_DES\Images</FilePath>
	<FilePath>I:\textures\</FilePath>
	<FilePath>I:\3ds\</FilePath>
	<FilePath>I:\media\architecture\</FilePath>
	<FilePath>C:\WINDOWS\Fonts\</FilePath>
	<ActiveViewerIndex>0</ActiveViewerIndex>
	<ActiveGroupIndex>0</ActiveGroupIndex>
	<Group>
	<Name>RootGroup</Name>
	<Ref>
	<RefName>Scene</RefName>
	<EntityType>Group</EntityType>
	<RefType>AddChild</RefType></Ref></Group>
	<Group>
	<Name>Scene</Name>
	<Ref>
	<RefName>ClearNode1</RefName>
	<EntityType>ClearNode</EntityType>
	<RefType>AddChild</RefType></Ref>
	<Ref>
	<RefName>LS1PAT</RefName>
	<EntityType>PAT</EntityType>
	<RefType>AddChild</RefType></Ref>
	<Ref>
	<RefName>LS2PAT</RefName>
	<EntityType>PAT</EntityType>
	<RefType>AddChild</RefType></Ref>
	<Ref>
	<RefName>LS3PAT</RefName>
	<EntityType>PAT</EntityType>
	<RefType>AddChild</RefType></Ref>
	<Ref>
	<RefName>Sphere1PAT</RefName>
	<EntityType>PAT</EntityType>
	<RefType>AddChild</RefType></Ref>
	<Ref>
	<RefName>Sphere2PAT</RefName>
	<EntityType>PAT</EntityType>
	<RefType>AddChild</RefType></Ref>
	<Ref>
	<RefName>Sphere3PAT</RefName>
	<EntityType>PAT</EntityType>
	<RefType>AddChild</RefType></Ref>
	<Ref>
	<RefName>Sphere4PAT</RefName>
	<EntityType>PAT</EntityType>
	<RefType>AddChild</RefType></Ref>
	<Ref>
	<RefName>Sphere5PAT</RefName>
	<EntityType>PAT</EntityType>
	<RefType>AddChild</RefType></Ref>
	<Ref>
	<RefName>Box1PAT</RefName>
	<EntityType>PAT</EntityType>
	<RefType>AddChild</RefType></Ref>
	<Ref>
	<RefName>Cone1PAT</RefName>
	<EntityType>PAT</EntityType>
	<RefType>AddChild</RefType></Ref>
	<Ref>
	<RefName>Cylinder1PAT</RefName>
	<EntityType>PAT</EntityType>
	<RefType>AddChild</RefType></Ref>
	<Ref>
	<RefName>HUDProjectionMatrix</RefName>
	<EntityType>Projection</EntityType>
	<RefType>AddChild</RefType></Ref></Group>
	<Viewer>
	<Name>Viewer1</Name>
	<CameraManipulator>OrbitManipulator</CameraManipulator>
	<SetCullMask>2</SetCullMask>
	<SetUpViewInWindow>
	<x>50</x>
	<y>50</y>
	<width>1024</width>
	<height>768</height></SetUpViewInWindow></Viewer>
	<ClearNode>
	<Name>ClearNode1</Name>
	<ClearColor>
	<x>0.1</x>
	<y>0.3</y>
	<z>0.1</z>
	<w>1</w></ClearColor></ClearNode>
	<Material>
	<Name>White</Name>
	<Diffuse>
	<x>1</x>
	<y>1</y>
	<z>1</z>
	<w>1</w></Diffuse>
	<Specular>
	<x>0.1</x>
	<y>0.1</y>
	<z>0.1</z>
	<w>1</w></Specular>
	<Ambient>
	<x>0.1</x>
	<y>0.1</y>
	<z>0.1</z>
	<w>1</w></Ambient>
	<Emission>
	<x>0.1</x>
	<y>0.1</y>
	<z>0.1</z>
	<w>1</w></Emission>
	<Shininess>25</Shininess></Material>
	<Light>
	<Name>L1</Name>
	<Position>
	<x>0</x>
	<y>0</y>
	<z>0</z>
	<w>1</w></Position>
	<Diffuse>
	<x>1</x>
	<y>0</y>
	<z>0</z>
	<w>1</w></Diffuse>
	<Specular>
	<x>0.5</x>
	<y>0.5</y>
	<z>0.5</z>
	<w>1</w></Specular>
	<Ambient>
	<x>0.5</x>
	<y>0.5</y>
	<z>0.5</z>
	<w>1</w></Ambient></Light>
	<Light>
	<Name>L2</Name>
	<Position>
	<x>0</x>
	<y>0</y>
	<z>0</z>
	<w>1</w></Position>
	<Diffuse>
	<x>0</x>
	<y>1</y>
	<z>0</z>
	<w>1</w></Diffuse>
	<Specular>
	<x>0.5</x>
	<y>0.5</y>
	<z>0.5</z>
	<w>1</w></Specular>
	<Ambient>
	<x>0</x>
	<y>0</y>
	<z>0</z>
	<w>1</w></Ambient></Light>
	<Light>
	<Name>L3</Name>
	<Position>
	<x>0</x>
	<y>0</y>
	<z>0</z>
	<w>1</w></Position>
	<Diffuse>
	<x>0</x>
	<y>0</y>
	<z>1</z>
	<w>1</w></Diffuse>
	<Specular>
	<x>0.5</x>
	<y>0.5</y>
	<z>0.5</z>
	<w>1</w></Specular>
	<Ambient>
	<x>0</x>
	<y>0</y>
	<z>0</z>
	<w>1</w></Ambient></Light>
	<LightSource>
	<Name>LS1</Name>
	<Ref>
	<RefName>L1</RefName>
	<EntityType>Light</EntityType>
	<RefType>SetLight</RefType></Ref>
	<Ref>
	<RefName>RootGroup</RefName>
	<EntityType>Group</EntityType>
	<RefType>SetStateSetModesOn</RefType></Ref>
	<SetLocalStateSetModes>ON</SetLocalStateSetModes></LightSource>
	<LightSource>
	<Name>LS2</Name>
	<Ref>
	<RefName>L2</RefName>
	<EntityType>Light</EntityType>
	<RefType>SetLight</RefType></Ref>
	<Ref>
	<RefName>RootGroup</RefName>
	<EntityType>Group</EntityType>
	<RefType>SetStateSetModesOn</RefType></Ref>
	<SetLocalStateSetModes/></LightSource>
	<LightSource>
	<Name>LS3</Name>
	<Ref>
	<RefName>L3</RefName>
	<EntityType>Light</EntityType>
	<RefType>SetLight</RefType></Ref>
	<Ref>
	<RefName>RootGroup</RefName>
	<EntityType>Group</EntityType>
	<RefType>SetStateSetModesOn</RefType></Ref>
	<SetLocalStateSetModes/></LightSource>
	<PositionAttitudeTransform>
	<Name>LS1PAT</Name>
	<Ref>
	<RefName>LS1</RefName>
	<EntityType>LightSource</EntityType>
	<RefType>AddChild</RefType></Ref>
	<Position>
	<x>0</x>
	<y>0</y>
	<z>5</z></Position>
	<Scale>
	<x>0.1</x>
	<y>0.1</y>
	<z>0.1</z></Scale></PositionAttitudeTransform>
	<PositionAttitudeTransform>
	<Name>LS2PAT</Name>
	<Ref>
	<RefName>LS2</RefName>
	<EntityType>LightSource</EntityType>
	<RefType>AddChild</RefType></Ref>
	<Position>
	<x>0</x>
	<y>5</y>
	<z>0</z></Position>
	<Scale>
	<x>0.1</x>
	<y>0.1</y>
	<z>0.1</z></Scale></PositionAttitudeTransform>
	<PositionAttitudeTransform>
	<Name>LS3PAT</Name>
	<Ref>
	<RefName>LS3</RefName>
	<EntityType>LightSource</EntityType>
	<RefType>AddChild</RefType></Ref>
	<Position>
	<x>5</x>
	<y>0</y>
	<z>0</z></Position>
	<Scale>
	<x>0.1</x>
	<y>0.1</y>
	<z>0.1</z></Scale></PositionAttitudeTransform>
	<PositionAttitudeTransform>
	<Name>GeodeLine1PAT</Name>
	<Ref>
	<RefName>GeodeLine1</RefName>
	<EntityType>Geode</EntityType>
	<RefType>AddChild</RefType></Ref>
	<Position>
	<x>0</x>
	<y>0</y>
	<z>0</z></Position>
	<Scale>
	<x>1</x>
	<y>1</y>
	<z>1</z></Scale></PositionAttitudeTransform>
	<PositionAttitudeTransform>
	<Name>Sphere1PAT</Name>
	<Ref>
	<RefName>Sphere1</RefName>
	<EntityType>Geode</EntityType>
	<RefType>AddChild</RefType></Ref>
	<Position>
	<x>0</x>
	<y>0</y>
	<z>0</z></Position>
	<Scale>
	<x>1</x>
	<y>1</y>
	<z>1</z></Scale></PositionAttitudeTransform>
	<PositionAttitudeTransform>
	<Name>Sphere2PAT</Name>
	<Ref>
	<RefName>Sphere1</RefName>
	<EntityType>Geode</EntityType>
	<RefType>AddChild</RefType></Ref>
	<Position>
	<x>0</x>
	<y>0</y>
	<z>5</z></Position>
	<Scale>
	<x>0.5</x>
	<y>1</y>
	<z>0.5</z></Scale></PositionAttitudeTransform>
	<PositionAttitudeTransform>
	<Name>Sphere3PAT</Name>
	<Ref>
	<RefName>Sphere1</RefName>
	<EntityType>Geode</EntityType>
	<RefType>AddChild</RefType></Ref>
	<Position>
	<x>0</x>
	<y>0</y>
	<z>10</z></Position>
	<Scale>
	<x>0.2</x>
	<y>0.9</y>
	<z>0.2</z></Scale></PositionAttitudeTransform>
	<PositionAttitudeTransform>
	<Name>Sphere4PAT</Name>
	<Ref>
	<RefName>Sphere1</RefName>
	<EntityType>Geode</EntityType>
	<RefType>AddChild</RefType></Ref>
	<Position>
	<x>0</x>
	<y>0</y>
	<z>20</z></Position>
	<Scale>
	<x>1</x>
	<y>1</y>
	<z>1</z></Scale></PositionAttitudeTransform>
	<PositionAttitudeTransform>
	<Name>Sphere5PAT</Name>
	<Ref>
	<RefName>Sphere1</RefName>
	<EntityType>Geode</EntityType>
	<RefType>AddChild</RefType></Ref>
	<Position>
	<x>0</x>
	<y>0</y>
	<z>20</z></Position>
	<Scale>
	<x>1</x>
	<y>1</y>
	<z>1</z></Scale></PositionAttitudeTransform>
	<PositionAttitudeTransform>
	<Name>Box1PAT</Name>
	<Ref>
	<RefName>Box1</RefName>
	<EntityType>Geode</EntityType>
	<RefType>AddChild</RefType></Ref>
	<Position>
	<x>-5</x>
	<y>0</y>
	<z>0</z></Position>
	<Scale>
	<x>1</x>
	<y>1</y>
	<z>1</z></Scale></PositionAttitudeTransform>
	<PositionAttitudeTransform>
	<Name>Capsule1PAT</Name>
	<Ref>
	<RefName>Capsule1</RefName>
	<EntityType>Geode</EntityType>
	<RefType>AddChild</RefType></Ref>
	<Position>
	<x>0</x>
	<y>5</y>
	<z>0</z></Position>
	<Scale>
	<x>1</x>
	<y>1</y>
	<z>1</z></Scale></PositionAttitudeTransform>
	<PositionAttitudeTransform>
	<Name>Cone1PAT</Name>
	<Ref>
	<RefName>Cone1</RefName>
	<EntityType>Geode</EntityType>
	<RefType>AddChild</RefType></Ref>
	<Position>
	<x>0</x>
	<y>-5</y>
	<z>0</z></Position>
	<Scale>
	<x>1</x>
	<y>1</y>
	<z>1</z></Scale></PositionAttitudeTransform>
	<PositionAttitudeTransform>
	<Name>Cylinder1PAT</Name>
	<Ref>
	<RefName>Cylinder1</RefName>
	<EntityType>Geode</EntityType>
	<RefType>AddChild</RefType></Ref>
	<Position>
	<x>10</x>
	<y>0</y>
	<z>0</z></Position>
	<Scale>
	<x>1</x>
	<y>1</y>
	<z>1</z></Scale></PositionAttitudeTransform>
	<Vec3Array>
	<Name>Vec3Array1</Name>
	<Vec3d>
	<x>0</x>
	<y>0</y>
	<z>0</z></Vec3d>
	<Vec3d>
	<x>0</x>
	<y>0</y>
	<z>50</z></Vec3d>
	<Vec3d>
	<x>0</x>
	<y>0</y>
	<z>0</z></Vec3d>
	<Vec3d>
	<x>0</x>
	<y>50</y>
	<z>0</z></Vec3d>
	<Vec3d>
	<x>0</x>
	<y>0</y>
	<z>0</z></Vec3d>
	<Vec3d>
	<x>50</x>
	<y>0</y>
	<z>0</z></Vec3d></Vec3Array>
	<DrawArrays>
	<Name>DrawArrays1</Name>
	<PrimitiveSet>LINE_STRIP</PrimitiveSet>
	<SetFirst>0</SetFirst>
	<SetCount>6</SetCount></DrawArrays>
	<Geometry>
	<Name>Geometry1</Name>
	<Ref>
	<RefName>DrawArrays1</RefName>
	<EntityType>DrawArrays</EntityType>
	<RefType>AddPrimitiveSet</RefType></Ref>
	<Ref>
	<RefName>Vec3Array1</RefName>
	<EntityType>Vec3Array</EntityType>
	<RefType>SetVertexArray</RefType></Ref></Geometry>
	<Geode>
	<Name>GeodeLine1</Name>
	<Ref>
	<RefName>Geometry1</RefName>
	<EntityType>Geometry</EntityType>
	<RefType>AddDrawable</RefType></Ref>
	<Ref>
	<RefName>White</RefName>
	<EntityType>Material</EntityType>
	<RefType>SetAttribute</RefType></Ref>
	<SetNodeMask>-1</SetNodeMask></Geode>
	<Geode>
	<Name>Sphere1</Name>
	<Ref>
	<RefName>White</RefName>
	<EntityType>Material</EntityType>
	<RefType>SetAttribute</RefType></Ref>
	<Sphere>
	<Center>
	<x>0</x>
	<y>0</y>
	<z>0</z></Center>
	<Radius>1</Radius></Sphere>
	<SetNodeMask>-1</SetNodeMask></Geode>
	<Geode>
	<Name>Box1</Name>
	<Ref>
	<RefName>White</RefName>
	<EntityType>Material</EntityType>
	<RefType>SetAttribute</RefType></Ref>
	<Box>
	<Center>
	<x>0</x>
	<y>0</y>
	<z>0</z></Center>
	<x>1</x>
	<y>1</y>
	<z>1</z></Box>
	<SetNodeMask>-1</SetNodeMask></Geode>
	<Geode>
	<Name>Capsule1</Name>
	<Ref>
	<RefName>White</RefName>
	<EntityType>Material</EntityType>
	<RefType>SetAttribute</RefType></Ref>
	<Capsule>
	<Center>
	<x>0</x>
	<y>0</y>
	<z>0</z></Center>
	<Radius>1</Radius>
	<Height>1</Height></Capsule>
	<SetNodeMask>-1</SetNodeMask></Geode>
	<Geode>
	<Name>Cone1</Name>
	<Ref>
	<RefName>White</RefName>
	<EntityType>Material</EntityType>
	<RefType>SetAttribute</RefType></Ref>
	<Cone>
	<Center>
	<x>0</x>
	<y>0</y>
	<z>0</z></Center>
	<Radius>1</Radius>
	<Height>1</Height></Cone>
	<SetNodeMask>-1</SetNodeMask></Geode>
	<Geode>
	<Name>Cylinder1</Name>
	<Ref>
	<RefName>White</RefName>
	<EntityType>Material</EntityType>
	<RefType>SetAttribute</RefType></Ref>
	<Cylinder>
	<Center>
	<x>0</x>
	<y>0</y>
	<z>0</z></Center>
	<Radius>1</Radius>
	<Height>1</Height></Cylinder>
	<SetNodeMask>-1</SetNodeMask></Geode>
	<Geode>
	<Name>HUD_Geode</Name>
	<Ref>
	<RefName>T1</RefName>
	<EntityType>Text</EntityType>
	<RefType>AddDrawable</RefType></Ref>
	<SetNodeMask>-1</SetNodeMask></Geode>
	<Text>
	<Name>T1</Name>
	<CharacterSize>25</CharacterSize>
	<Font>C:\Windows\Fonts\impact.ttf</Font>
	<InitText>Primitives</InitText>
	<AxisAlignment>SCREEN</AxisAlignment>
	<Position>
	<x>10</x>
	<y>10</y>
	<z>-1.5</z></Position>
	<Color>
	<x>199</x>
	<y>77</y>
	<z>15</z>
	<w>1</w></Color></Text>
	<Projection>
	<Name>HUDProjectionMatrix</Name>
	<Ref>
	<RefName>HUDModelViewMatrix</RefName>
	<EntityType>MatrixTransform</EntityType>
	<RefType>AddChild</RefType></Ref>
	<Ortho2D>
	<Left>-0</Left>
	<Right>1024</Right>
	<Top>768</Top>
	<Bottom>-0</Bottom></Ortho2D></Projection>
	<MatrixTransform>
	<Name>HUDModelViewMatrix</Name>
	<Ref>
	<RefName>HUD_Geode</RefName>
	<EntityType>Geode</EntityType>
	<RefType>AddChild</RefType></Ref>
	<ReferenceFrame>ABSOLUTE_RF</ReferenceFrame>
	<Identity>TRUE</Identity></MatrixTransform>
	<MemoryMapServer>
	<Name>MJSRTF_Server</Name>
	<MemoryMapName>MJSRTF</MemoryMapName>
	<Size>1</Size></MemoryMapServer>
	<MemoryMapClient>
	<Name>MJSRTF_LocalClient</Name>
	<MemoryMapName>MJSRTF</MemoryMapName></MemoryMapClient></Environment>